{
  "hash": "d7cbfc84",
  "configHash": "ab449806",
  "lockfileHash": "0151209c",
  "browserHash": "f8bc419c",
  "optimized": {
    "react/jsx-dev-runtime": {
      "src": "../../node_modules/react/jsx-dev-runtime.js",
      "file": "react_jsx-dev-runtime.js",
      "fileHash": "0bc2c041",
      "needsInterop": true
    },
    "react": {
      "src": "../../node_modules/react/index.js",
      "file": "react.js",
      "fileHash": "57ba5f09",
      "needsInterop": true
    },
    "react-dom/client": {
      "src": "../../node_modules/react-dom/client.js",
      "file": "react-dom_client.js",
      "fileHash": "c532beba",
      "needsInterop": true
    }
  },
  "chunks": {
    "chunk-B2WE2YPZ": {
      "file": "chunk-B2WE2YPZ.js"
    }
  }
}